Metadata-Version: 2.4
Name: agentik-framework
Version: 1.1.5
Summary: Agentik - a CLI-first, modular agent framework that runs LLMs via OpenRouter.
Author-email: Vinay Joshi <joshivinay822@gmail.com>, Avinash Raghuvanshi <avi95461@gmail.com>
License: MIT
Keywords: agents,cli,llm,openrouter,framework,automation
Classifier: Development Status :: 3 - Alpha
Classifier: Intended Audience :: Developers
Classifier: License :: OSI Approved :: MIT License
Classifier: Programming Language :: Python :: 3
Classifier: Programming Language :: Python :: 3.10
Classifier: Programming Language :: Python :: 3.11
Classifier: Programming Language :: Python :: 3.12
Classifier: Topic :: Software Development :: Libraries
Classifier: Topic :: Utilities
Requires-Python: >=3.10
License-File: LICENCE
Requires-Dist: typer>=0.12.3
Requires-Dist: rich>=13.7.1
Requires-Dist: pydantic>=2.7
Requires-Dist: pyyaml>=6.0.1
Requires-Dist: python-dotenv>=1.0.1
Requires-Dist: httpx>=0.27.0
Requires-Dist: jinja2>=3.1.3
Requires-Dist: jsonschema>=4.22.0
Provides-Extra: dev
Requires-Dist: pytest>=8.2; extra == "dev"
Requires-Dist: pytest-cov>=5.0; extra == "dev"
Requires-Dist: ruff>=0.5.5; extra == "dev"
Requires-Dist: black>=24.4.2; extra == "dev"
Requires-Dist: build>=1.2.1; extra == "dev"
Requires-Dist: twine>=5.1.1; extra == "dev"
Requires-Dist: mypy>=1.10; extra == "dev"
Dynamic: license-file
